eleven_pp-1.2.1.dist-info/METADATA
eleven_pp-1.2.1.dist-info/WHEEL
eleven_pp-1.2.1.dist-info/entry_points.txt
eleven_pp/__init__.py
eleven_pp/dday.py
eleven_pp/lotto.py
eleven_pp/rec_resto.py
eleven_pp/rink.py
eleven_pp-1.2.1.dist-info/RECORD
